verslilietuvadb
