Metadata-Version: 2.1
Name: verslilietuvadb
Version: 0.0.4
Summary: Versli Lietuva EDB controller.
Home-page: https://gitlab.com/wefindx/verslilietuvaedb
Author: Mindey
Author-email: mindey@qq.com
License: ASK FOR PERMISSIONS
Platform: UNKNOWN
Provides-Extra: test
